nonebot_plugin_ntqq_restart/__init__.py
nonebot_plugin_ntqq_restart/__main__.py
nonebot_plugin_ntqq_restart/config.py
nonebot_plugin_ntqq_restart/utils.py
nonebot_plugin_ntqq_restart/models/__init__.py
nonebot_plugin_ntqq_restart/models/process.py
nonebot_plugin_ntqq_restart-0.2.2.dist-info/LICENSE
nonebot_plugin_ntqq_restart-0.2.2.dist-info/METADATA
nonebot_plugin_ntqq_restart-0.2.2.dist-info/WHEEL
nonebot_plugin_ntqq_restart-0.2.2.dist-info/top_level.txt
nonebot_plugin_ntqq_restart-0.2.2.dist-info/RECORD
