Metadata-Version: 2.1
Name: nonebot_plugin_ntqq_restart
Version: 0.2.2
Summary: A plugin for restarting NTQQ when bot disconnection
Author-email: KanbeReina <kano.2525@qq.com>
License: MIT
Requires-Python: >=3.10
License-File: LICENSE
Requires-Dist: psutil >=6.0.0
Requires-Dist: pywin32 >=306
Requires-Dist: pyautoit >=0.6.5
Requires-Dist: nonebot-plugin-apscheduler >=0.5.0
Requires-Dist: nonebot2 >=2.3.2
